MANIFEST.in
setup.cfg
setup.py
tw/__init__.py
tw.mochikit.egg-info/PKG-INFO
tw.mochikit.egg-info/SOURCES.txt
tw.mochikit.egg-info/dependency_links.txt
tw.mochikit.egg-info/entry_points.txt
tw.mochikit.egg-info/namespace_packages.txt
tw.mochikit.egg-info/not-zip-safe
tw.mochikit.egg-info/requires.txt
tw.mochikit.egg-info/top_level.txt
tw/mochikit/__init__.py
tw/mochikit/descriptions.py
tw/mochikit/release.py
tw/mochikit/static/Async.js
tw/mochikit/static/Base.js
tw/mochikit/static/Color.js
tw/mochikit/static/Controls.js
tw/mochikit/static/DOM.js
tw/mochikit/static/DateTime.js
tw/mochikit/static/DragAndDrop.js
tw/mochikit/static/Format.js
tw/mochikit/static/Iter.js
tw/mochikit/static/Logging.js
tw/mochikit/static/LoggingPane.js
tw/mochikit/static/MochiKit.js
tw/mochikit/static/MockDOM.js
tw/mochikit/static/Position.js
tw/mochikit/static/Selector.js
tw/mochikit/static/Signal.js
tw/mochikit/static/Sortable.js
tw/mochikit/static/Style.js
tw/mochikit/static/Test.js
tw/mochikit/static/Visual.js
tw/mochikit/static/__package__.js
tw/mochikit/static/packed/MochiKit.js
tw/mochikit/static/packed/__package__.js