Metadata-Version: 1.0
Name: tw.mochikit
Version: 0.8
Summary: MochiKit 1.4 (dev) widget for ToscaWidgets
Home-page: http://toscawidgets.org
Author: Alberto Valverde Gonzalez
Author-email: alberto@toscat.net
License: UNKNOWN
Download-URL: http://toscawidgets.org/download
Keywords: toscawidgets.widgets
Platform: UNKNOWN
